{
  "name" : "downloads_2020-04-05_84_hadrup2020.pdf",
  "metadata" : {
    "source" : "CRF",
    "title" : "Acute Phase Response as a Biological Mechanism-of- Action of (Nano)particle-Induced Cardiovascular Disease",
    "authors" : [ "Niels Hadrup", "Vadim Zhernovkov", "Nicklas Raun Jacobsen", "Carola Voss", "Maximilian Strunz", "Meshal Ansari", "Herbert B. Schiller", "Sabina Halappanavar", "Sarah S. Poulsen", "Boris Kholodenko", "Tobias Stoeger", "Anne Thoustrup Saber", "Ulla Vogel" ],
    "emails" : [ "ubv@nfa.dk" ],
    "sections" : [ {
      "heading" : null,
      "text" : "1907476 (1 of 12) © 2020 WILEY-VCH Verlag GmbH & Co. KGaA, Weinheim\nwww.small-journal.com\nReview\nAcute Phase Response as a Biological Mechanism-ofAction of (Nano)particle-Induced Cardiovascular Disease\nNiels Hadrup, Vadim Zhernovkov, Nicklas Raun Jacobsen, Carola Voss, Maximilian Strunz, Meshal Ansari, Herbert B. Schiller, Sabina Halappanavar, Sarah S. Poulsen, Boris Kholodenko, Tobias Stoeger, Anne Thoustrup Saber, and Ulla Vogel*\nDr. N. Hadrup, Dr. N. R. Jacobsen, Dr. S. S. Poulsen, Dr. A. T. Saber, Prof. U. Vogel National Research Centre for the Working Environment Copenhagen DK-2100, Denmark E-mail: ubv@nfa.dk Dr. V. Zhernovkov, Prof. B. Kholodenko Systems Biology Ireland University College Dublin Dublin 4, Ireland Dr. C. Voss, Dr. M. Strunz, Dr. M. Ansari, Dr. H. B. Schiller, Dr. T. Stoeger Comprehensive Pneumology Center (CPC)/Institute of Lung Biology and Disease (ILBD) Helmholtz Zentrum München Member of the German Center for Lung Research (DZL) Neuherberg D-85764, Germany Dr. S. Halappanavar Environmental Health Science and Research Bureau Health Canada Ottawa, ON K1A 0K9, Canada Prof. U. Vogel DTU Health Technical University of Denmark Kgs. Lyngby DK-2800, Denmark\nThe ORCID identification number(s) for the author(s) of this article can be found under https://doi.org/10.1002/smll.201907476.\nDOI: 10.1002/smll.201907476\n1. Introduction\nInhalation of particulate air pollution is associated with mortality and morbidity[1–5] and cardiovascular disease constitutes a major fraction of the particle-induced morbidity.[6] In a famous study by Clancy et  al.,[6] the effect of banning coal-heating in private households in Dublin, Ireland in 1991 was followed\nInhaled nanoparticles constitute a potential health hazard due to their size-dependent lung deposition and large surface to mass ratio. Exposure to high levels contributes to the risk of developing respiratory and cardiovascular diseases, as well as of lung cancer. Particle-induced acute phase response may be an important mechanism of action of particleinduced cardiovascular disease. Here, the authors review new important scientific evidence showing causal relationships between inhalation of particle and nanomaterials, induction of acute phase response, and risk of cardiovascular disease. Particle-induced acute phase response provides a means for risk assessment of particle-induced cardiovascular disease and underscores cardiovascular disease as an occupational disease.\nby comparing mortality rates 6 years before and after the ban. The ban was very efficient as the level of black smoke was reduced by 0.036  mg m−3 (70%). The average mortality rate was reduced by 75 per 100  000 person-years (adjusted for the mortality in the rest of Ireland, where no ban was implemented). Importantly, 77% of the reduced mortality was cardiovascular.\nEvidence suggests that inhalation of nanoparticles is more hazardous than inhalation of larger particles with the same chemical composition.[7] This is because nanoparticles possess an ultrahigh surface to mass ratio[8] and have a higher\ndeposition rate in the alveolar region of the lung, where clearance is low.[9] Nanoparticles are consequently removed more slowly from the lung compared to larger particles (at the same air concentration by mass),[10] resulting in prolonged presence of the nanoparticles in the alveolar region of the lung.[10,11] This leads to long-lasting pulmonary presence of particles with large total surface area. The prolonged presence, in turn, causes inflammation, which is proportional to the total surface area of the deposited particles.[8,12] We have previously reported that the strongest transcriptional response in lung tissue from mice exposed to TiO2 nanoparticles or carbon nanotubes is a pulmonary acute phase response.[11,13,14] Acute phase response activation is a well-known risk factor for cardiovascular disease.[15,16] In this article, we review a number of recent animal and human studies that strengthen our previously proposed mechanism of particle-induced pulmonary acute phase response as a mechanism of action of particle-related cardiovascular disease.[17]\nThe acute phase response was originally defined as a group of physiologic, systemic changes induced by infection and tissue injury.[15] Conditions that commonly lead to induction of the acute phase response include infection, trauma, burns, tissue infarction as well as inflammatory diseases and advanced cancer.[15] Acute phase proteins are defined as serum proteins whose plasma levels increase or decrease by at least 25% during an inflammatory disorder. Gabay and Kushner listed 39 different human acute phase proteins including members of the complement system, proteins involved in coagulation and fibrinolysis, antiproteases, transport proteins, and inflammatory mediators.[15] Serum Amyloid A (SAA) and C-reactive protein (CRP) are the most dynamically regulated acute phase proteins and can be upregulated more than 1000-fold during an acute\nSmall 2020, 1907476\n1907476 (2 of 12)\nwww.advancedsciencenews.com\n© 2020 WILEY-VCH Verlag GmbH & Co. KGaA, Weinheim\nwww.small-journal.com\nphase response.[15] Humans have two inducible SAA isoforms, SAA1 and SAA2, whereas mice express three isoforms, Saa1, Saa2, and Saa3.[18] Interestingly, rats do not express Saa genes, whereas Crp is only moderately inducible in mice.[19]\nBoth SAA and CRP are risk factors for coronary heart disease in prospective, epidemiological studies.[20] In the Nurses’ Health Study, SAA and CRP levels at baseline were predictive of increased risk for cardiovascular events defined as death from coronary heart disease, nonfatal myocardial infarction or stroke, or the need for coronary-revascularization procedures. A fivefold increase in the levels of SAA was associated with threefold increased risk of cardiovascular events.[20] Serum levels of CRP and SAA are highly correlated in humans.[21–23] However, CRP is likely not causally related to risk of cardiovascular disease, since genetic variation in CRP are associated with variations in blood levels of CRP but not with risk of coronary heart disease.[24–26] This suggests that CRP is not causally related to cardiovascular disease, but co-vary with the causal factor, which could be SAA.\n2. Proposed Mechanism of Action: Serum Amyloid A Directly Promotes Atherosclerosis SAA are pleiotropic proteins that also have cytokine-like pro-inflammatory activities and can signal through several cell surface receptors including TLR2, TLR4, CD36, FPR2, RAGE, and P2XY.[27] Under sterile conditions, SAA can stimulate the NLRP3 inflammasome of phagocytes to produce high levels of TNFα, IL1a, IL1b, and IL6, important cytokines of the acute phase response.[28] During the acute phase response, SAA becomes incorporated into high-density lipoproteins (HDL), thereby replacing Apolipoprotein A-1 especially at high SAA concentrations.[18,29] An activated acute phase response inhibits reverse cholesterol transport in humans and mice.[30,31] Reverse cholesterol transport is a major anti-atherogenic activity of HDL, where HDL removes excess cholesterol from peripheral cells and transports the cholesterol back to the liver for subsequent excretion into bile and feces.[30] The SAA-mediated inhibition of reverse cholesterol transport results in increased cholesterol sequestering in peripheral cells including macrophages, turning them into foam cells.[32]\nSAA has been shown to be causally implicated in atherosclerosis. Inactivation of all three SAA isoforms decreases atherosclerosis in ApoE –/– mice,[33] a commonly used mouse model of atherosclerosis, whereas overexpression of Saa1[34,35] and Saa3[33] increases atherosclerosis in ApoE –/– mice. This shows that SAA expression is implicated in the formation of plaques in ApoE –/– mice. Inactivation of only Saa1 and Saa2 did not affect the basal level of atherosclerosis,[36] indicating that the three isoforms have overlapping functions and are likely all pro-atherogenic.\nThus, SAA inhibits reverse cholesterol transport and stimulates macrophage foam cell formation, and promotes plaque formation and thereby atherosclerosis.\n3. Particle-Induced Acute Phase Response The clinical manifestation of acute phase response includes fever, leukocytosis, increased vascular permeability and\nincreased serum levels of acute phase proteins. However, the proteins in systemic circulation can originate from various organs and the organ of production can only be identified by increased levels of transcription of acute phase response genes in organ tissue or specific cells.\nThe acute phase response following inhalation of particles initiates at the transcriptional level in the lung. Inhalation\nAnne Thoustrup Saber is senior researcher at the National Research Centre for the Working Environment and PI of past and present national studies related to nanosafety. She has also been participant in EU projects related to nanosafety. She is trained as chemical engineer and human biologist. She has worked with\nthe toxicology of particles since 2000. She has been the Danish member of the Nordic Expert Group for Criteria Documentation of Health Risks from Chemicals (NEG) since 2008.\nUlla Vogel is group leader at the National Research Centre for the Working Environment, PI of Danish Centre for Nanosafety 1 and 2 (2012–2019) and participant in past and present H2020 projects related to nanosafety. She is trained as biochemist, molecular biologist and certified ERT toxicologist. She has worked with\nmolecular epidemiology and the toxicology of inhaled aerosols including nano particles with focus on effects in lungs and secondary target organs (cardiovascular, liver, blood) since 1997. She is advisor to the Danish Working Environment Authority on toxicology.\nTobias Stoeger is a group leader at the Helmholtz Zentrum MünchenGerman Research Center for Environmental Health. His research is focused on the toxicity of nanoparticles and alveolar mechanisms of sterile, pulmonary inflammation. Tobias has co-authored over 90 scientific articles.\nSmall 2020, 1907476\n1907476 (3 of 12)\nwww.advancedsciencenews.com\n© 2020 WILEY-VCH Verlag GmbH & Co. KGaA, Weinheim\nwww.small-journal.com\nexposure to TiO2 nanoparticle for 1 h daily for 11 days induced pulmonary acute phase response but no hepatic acute phase response 5 days after last exposure day.[11] In the lung tissue, global transcriptional profiling showed that the acute phase gene Saa3 was the most differentially regulated gene,[11,37] but Saa3, Saa1, and Saa2 were all highly expressed in lung tissue following pulmonary exposure to TiO2 and carbon black nanoparticles as well as multiwalled carbon nanotubes.[13,17,38] Pulmonary Saa3 mRNA expression has been shown to correlate with blood levels of SAA3 following pulmonary exposure to carbon nanotubes[39] and pulmonary Saa3 expression was paralleled by increased blood levels of SAA3 following pulmonary exposure to carbon black, diesel exhaust particles, jet engine particles, and nanofibrillated cellulose.[38,40–42] It has been a central dogma that acute phase response proteins are primarily synthesized in the liver.[18,29] However, no hepatic acute phase response was detected in mice following inhalation exposure to 20  mg m−3 of Printex 90 carbon black nanoparticles or NIST2975 diesel exhaust particles for 90 min a day, for 4 consecutive days.[43] Instead, inhalation of carbon black and diesel exhaust particles induced a pulmonary acute phase response,[17,44] which for carbon was already detected after 24 h at concentrations of 380 µg m−3.[37]\nHepatic acute phase response has been detected 1 day after pulmonary exposure to multiwalled carbon nanotubes, but the acute phase response had diminished on day 3 post-exposure, in contrast to pulmonary Saa3 levels that remained elevated.[45] Saa1 was the most differentially expressed hepatic acute phase response following airway exposure to TiO2[46] and carbon nanotubes[39,47,48] and we use Saa1 mRNA levels as a biomarker of the hepatic acute phase response.[45] Pulmonary Saa3 mRNA expression levels were greater and lasted longer than hepatic Saa1 mRNA expression,[45] again suggesting that following pulmonary exposure, the pulmonary acute phase response is stronger and more long lasting than the hepatic acute phase response.\n4. Physico-Chemical Predictors of Particle-Induced Acute Phase Response SAA is a macrophage and neutrophil chemoattractant[49] and Saa mRNA levels in lung tissue correlates closely with neutrophil cell numbers in bronchoalveolar lavage fluid across particle type, dose level, time point and pulmonary dosing method (inhalation or instillation) in mice.[17,37,44,45,50] Particleinduced pulmonary inflammation in terms of neutrophil influx has been shown to correlate closely with total surface area of the deposited particles.[8,12,51] Similarly, Saa3 mRNA levels (and hence acute phase response) correlate with the total surface area of the deposited nanoparticles and carbon nanotubes.[17,45] In addition, plasma levels of SAA3 have been shown to correlate with Saa3 mRNA levels in lung tissue[13] and with neutrophil cell numbers in broncho-alveolar lavage fluid in mice exposed to multiwalled carbon nanotubes,[45] suggesting that SAA3 protein in plasma originates from the lung. This suggests that pulmonary transcription levels of acute phase response genes can be predicted by the deposited surface area of insoluble particles. Since the specific surface area of particle increases with\ndecreasing particle size, the pulmonary acute phase response may be predicted based on estimation of the particle deposition and retention in the alveolar region.\nThere is evidence suggesting that some types of inhalable materials induce much stronger acute phase response than predicted by the total deposited surface area. These include nanofibrillated cellulose,[42] graphene oxide[41] and soluble metal oxides such as ZnO.[52] Graphene oxide and nano-fibrillated cellulose are highly hydroxylated on the surface and therefore share structural similarities with lipopolysaccharide (LPS) a potent inducer of acute phase response,[53] and we have previously suggested that this may be the reason for the stronger acute phase response.[41,42] ZnO undergoes dissolution at the low pH in the lyzosomes, causing cytotoxicity in vivo and in vitro,[52,54] and this is a likely cause of the strong ZnO-induced acute phase response.\n5. Dose-Dependent, Particle-Induced Pulmonary Acute Phase Response We have consistently found that pulmonary exposure to nanomaterials by inhalation or by instillation induces a pulmonary acute phase response. The pulmonary acute phase response is dose-dependent, both in terms of the number of differentially regulated acute phase genes and in terms of the fold increase in the mRNA expression level of the most differentially regulated acute phase gene, Saa3.[17] The acute phase response is long lasting, as increased levels of Saa3 mRNA in lung tissue and SAA3 in plasma were detected 28 days after exposure to multiwalled carbon nanotubes[13,39,45] and increased Saa3 mRNA levels in lung tissue were detected 90 days after exposure to Printex90 carbon black nanoparticles.[41] We have used mRNA levels of Saa3 as biomarker of the pulmonary acute phase response.[44] Dose-dependent pulmonary acute phase response has been reported for many different nanoparticles and dusts including TiO2 particles,[14,17,55–58] carbon black,[38] carbon nanotubes,[13,44,45,59] combustion particles,[40,44,60] graphene oxide and reduce graphene oxide,[41] nano-fibrillated celluloses,[42] ZnO nanoparticles,[52] halloysite nanotubes[61] and sanding dust from paint and epoxy composites.[58,62] Figure 1 shows a heat map of the gene expression levels of 26 acute phase proteins following pulmonary exposure to different insoluble nanomaterials and asbestos. The list of genes were derived using supervised statistical analysis of gene expression data and the level of inflammation assessed by the percentage of neutrophils in the bronchoalveolar lavage fluid. The heat map shows the nanoparticles on the horizontal axis ordered according to the percentage of neutrophils and the acute phase response genes are listed on the vertical axis according to a score for how their expression correlates with neutrophil levels. The 26 acute phase proteins are briefly described in Table 1.\nOccupational exposure to various metal oxides including ZnO and CuO is known to induce metal fume fever in exposed workers.[66,67] In a controlled study of 16 healthy volunteers, Christian Monsé et  al.[68] demonstrated that inhalation of nanosized ZnO particles induces dose-dependent acute phase response in humans (Figure 2). The volunteers were exposed to\nSmall 2020, 1907476\n1907476 (4 of 12)\nwww.advancedsciencenews.com\n© 2020 WILEY-VCH Verlag GmbH & Co. KGaA, Weinheim\nwww.small-journal.com\n0, 0.5, 1, and 2 mg m−3 ZnO nanoparticles for 4 h on different days separated by 2 weeks. One day after exposure, CRP was statistically significantly increased at 2 mg m−3, and SAA levels were statistically significantly increased in a dose-dependent manner at 1 and 2 mg m−3 whereas 0.5 mg m−3 was identified as a no-effect-level (Figure  2). Notably, these exposure levels are well below current occupational exposure levels for ZnO (5  mg m−3 ZnO or 4  mg m−3 Zn), calling for re-evaluation of the occupational exposure limit.[69] Pulmonary exposure to ZnO nanoparticles in mice induced dose-dependent pulmonary acute phase response with similar no-effect-levels,[52] suggesting that studies in mice can be used for risk assessment of particleinduced acute phase response.\n6. Biomonitoring Studies of Occupational Exposure to Particles and Dust There are a limited number of occupational biomonitoring studies which included assessment of exposures to (nano) particles and dusts and measurements of SAA or CRP (Table 2). As can be seen from the studies, exposure to welding particles was consistently accompanied by increased blood levels of acute phase response proteins with the exception of metal inert gas (MIG) welding with aluminium.[70–76] This is consistent with the strong dose-response relationship observed following inhalation of ZnO nanoparticles.[68] Correlation between dust levels during steel production and iron foundry and blood levels of CRP or SAA have been observed.[77,78] Interestingly, dust from paper production also induced a strong acute phase response in workers following occupational exposure,[79] paralleled by a strong acute phase response in mice exposed to nano-fibrilliated cellulose.[42] For occupational exposure to combustion particles, both positive and negative studies were identified.[22,50,80–83] Taken together, occupational biomonitoring studies report increased blood levels of acute phase response proteins among workers following occupational exposure to particles especially in controlled studies, where the participants serve as their own control. In other studies, including cross-sectional studies, positive correlations between exposure to particles and acute phase response proteins CRP and SAA were found.\nSmall 2020, 1907476\n1907476 (5 of 12)\nwww.advancedsciencenews.com\n© 2020 WILEY-VCH Verlag GmbH & Co. KGaA, Weinheim\nwww.small-journal.com\nTaken together, the biomonitoring studies strongly suggest that occupational exposure to dust and particles leads to increased systemic acute phase response. The studies in mice furthermore suggest that the particle-induced acute phase response is long lasting for insoluble particles, which in occupational settings with re-occurring exposures would translate to a 45-year work-life. Since even very small increments in CRP and SAA levels are associated with significantly increase future risk of coronary heart disease in prospective studies, the observed correlations between occupational exposure to metal oxide particles and increased acute phase response warrants reassessment of occupational exposure to metal oxides and other exposures that entail induction of acute phase response.\n7. Serum Amyloid A and C-Reactive Protein as Biomarkers of Particle Exposure CRP is routinely used in the clinical practice as a biomarker of systemic inflammation,[86] and sensitive and reliable assays for detection of CRP and SAA are commercially available.[21] However, both SAA and CRP levels are influenced by many different factors including body mass index, smoking status, chronic inflammatory diseases, use of anti-inflammatory medicine and bacterial and viral infections.[15,22,23] Both bacterial infections leading to short-term large increases in blood levels of CRP and SAA, and long-term low-inflammatory conditions leading to small increases are associated with risk of cardiovascular disease.[86,87] While bacterial infections increase CRP and SAA levels by more than 1000-fold,[15] inhalation of occupationally relevant doses of ZnO increased CRP and SAA levels by a factor of 10,[68] and the effect of inhaled insoluble particles such as air pollution appears to be even smaller. Thus, in a study of the association between air pollution levels modelled from satellite-images and CRP levels in 30  034 participants, 5 µg m−3 PM2.5 increments were associated with 1.31% increase in CRP [95% confidence interval (CI): 1.00%, 1.63%) after adjusting for confounders.[88] Such small increments are often difficult to detect even in occupational biomonitoring studies[50,80,89] because large inter-individual variation in basal levels of CRP and SAA hampers the statistical power to detect exposure-related effects.[23] However, the inter-individual variation may be controlled for by adjusting SAA levels for CRP, thus using CRP as a biomarker of the individual baseline level of acute phase response.[22,23]\n8. Cells Expressing Acute Phase Response Proteins in the Lung For hazard and risk assessment purposes, specific test protocols and assays need to be developed. Sub-chronic and chronic inhalation studies for assessing lung cancer risk are usually performed in rats,[90] but rats may be an inappropriate model for assessment of particle-induced acute phase response in humans since rats do not express SAA. In addition, in vitro assays and high-throughput assays are preferred both from an animal welfare perspective and for economic reasons.\nSmall 2020, 1907476\nTable 1. List of the top ranked acute phase response genes according to their RF score and their potential functional role in the acute phase response.\nGene symbol RF score Gene name and function\nSaa1 0.6824159478 Serum Amyloid A1. Major acute phase protein\nOrm2 0.1241813132 Orosomucoid 2. Major acute phase protein\nSaa2 0.0971252625 Serum Amyloid A2. Major acute phase protein\nMmp3 0.0154310491 Matrix Metallopeptidase 3. The protein promotes neutrophil infiltration into the lung and plays an important role in acute inflammatory response\nLcn2 0.0120446052 Lipocalin 2. Iron-trafficking protein, acute kidney injury biomarker\nFth1 0.0115027576 Ferritin Heavy Chain 1. The protein mediates iron homeostasis\nSaa3 0.0094597367 Serum Amyloid A3. Major acute phase protein\nCcl17 0.0077724584 Chemokine (CC motif) ligand 17. Th2 CC chemokine ligand\nOrm1 0.0075323055 Orosomucoid 1. Major acute phase protein\nAnkrd1 0.0049984728 Ankyrin Repeat Domain 1. Ankrd1 is a transcription factor involved in regulation of downstream\nsignaling of pattern recognition receptors\nNfkbie 0.0041863373 NFKB Inhibitor Epsilon. Inhibitor of NF-kappa-B signaling\nC3 0.0040131412 Complement C3. Component of the complement system\nHpx 0.0034413209 Hemopexin. Major acute phase protein, mediates heme and iron homeostasis\nCtps 0.0025481592 CTP Synthase 1. Ctps induces proliferation of activated lymphocytes\nPtgs1 0.0025139002 Prostaglandin-Endoperoxide Synthase 1, Cyclooxygenase-1 (COX-1). Inflammatory\nlipid mediator\nTimp1 0.0020899172 TIMP Metallopeptidase Inhibitor 1. Timp1 regulates matrix metalloproteinases\nLgi2 0.0014406552 Leucine Rich Repeat LGI Family Member 2\nCstb 0.0013009519 Cystatin B. Protection against lysosomal protease leakage\nRbm3 0.0011968426 RNA Binding Motif Protein 3\nGlrx 0.0011255511 Glutaredoxin. The protein is considered as a sensor of oxidative stress mediated by H2O2.\nF10 0.0010072173 Coagulation Factor X\nRgs1 0.0009115299 Regulator of G Protein Signaling 1\nCd14 0.0005990058 CD14 Molecule. The protein encoded by this gene is a surface antigen that is mainly\nexpressed on monocytes/macrophages\n9030425E11Rik 0.0004969364 Clmp, CXADR-like membrane protein. Cell-cell adhesion protein\nCcl7 0.0003589204 CC Motif Chemokine Ligand 7. Ccl7 modulates acute neutrophilic lung inflammation\nCcl8 0.0003057048 CC Motif Chemokine Ligand 8. Chemotactic factor that attracts lymphocytes, monocytes,\neosinophils, and basophils\nRF score is the value of the feature importance derived from random forest regression classifier.\n1907476 (6 of 12)\nwww.advancedsciencenews.com\n© 2020 WILEY-VCH Verlag GmbH & Co. KGaA, Weinheim\nwww.small-journal.com\nA body of studies shows particle-induced induction of acute phase response in terms of increased Saa3 transcription and SAA3 release.[13,14,39,40,42,45,46,52,91–96] Furthermore, Saa3 mRNA levels were increased within a few hours and SAA3 protein was measured by ELISA as early as 6 h after LPS instillation accumulating up to 24 h before slowly declining to base levels over a course of days.[97] (unpublished data) However, all these studies were conducted in bronchoalveolar lavage or whole lung tissue, and the responsible cell types have not yet been identified. Early studies using models of endotoxin (LPS) triggered inflammation mainly suggested macrophages as the origin of extrahepatic Saa expression.[98] However, several different cell types in human lung are capable of expressing SAA including macrophages, epithelial cells and fibroblasts.[99] Thus, all three cell types expressed C-reactive protein (CRP), SAA1, SAA2, and SAA4. Transcript levels of CRP and SAA1 were highest in epithelial cells, whereas SAA2 and SAA4 transcript levels were highest in fibroblasts. However, particle-induced SAA transcription has not yet been shown in human lung tissue. Recent single-cell RNA sequencing data from murine lung tissue showed strong carbon nanoparticle-induced Saa3 transcription almost exclusively in mesenchymal cells, a cluster including fibroblasts and activated mesothelial cells, and to a much lesser extent in alveolar type 2 cells (Figure  3).\nSmall 2020, 1907476\n1907476 (7 of 12)\nwww.advancedsciencenews.com\n© 2020 WILEY-VCH Verlag GmbH & Co. KGaA, Weinheim\nwww.small-journal.com\nSmall 2020, 1907476\nVolunteers in emission chamber, Men (n = 12) MIG brazing fumes on three different exposure days (6 h), 1 week in-between each exposure, blood samples drawn before and 24 h after exposure. Each exposure was part of a stepwise decrease or increase in zinc\nconcentration starting with 0.9 mg zinc m−3, 1.43 mg PM10 m−3)\nCRP was increased after exposure to fumes with 1.2 and 1.5 mg m−3 zinc. No effect was\nobserved at 0.90 mg m zinc\nn/a [75]\nWelders at work (Sweden), Men (n = 101)\nA cross sectional study of 101 welders and 127 controls. Welding fumes were measured as respirable dust. Welders were exposed to a median of 1.1 mg m−3. The level among controls was lower than 0.1 mg m−3 No correlation between exposure and CRP\nSAA was positively associated with exposure to\nrespirable dust\n[76]\nDust from paper production\nWorkers in a pulp and paper mill at work (Sweden), Women (n = 10) and men (n = 62)\nDust while working at the mill. Personal sampling: 8-h-time-weighed average of 0.3 mg m−3 with\nthe highest exposure in the mixing department (3.3 mg m−3)\nRelation observed between CRP and exposure metrics:\nPM10, total, and inhalable dust\nRelation observed between SAA and exposure metrics:\nPM10, total, and inhalable dust\n[79]\nEmissions from steel/iron manufacturing\nSteel-production plant workers at work (Italy), Men (n = 37)\nPM1 and PM10 (coarse PM) measured in 11 different working areas. PM1 mean level: 0.008 mg m−3; PM10\nmean level: 0.262 mg m−3. Blood samples taken on the first and fourth day of a working week\nBoth PM1 and PM10 exposure was associated with increased\nCRP\nn/a [78]\nIron-foundry workers at work (Sweden), Women (n = 5) and men (n = 80)\nAverage 8-h time-weighted average air concentrations of respirable dust and quartz were 0.85 and 0.052 mg m−3, respectively. Aerosol and blood samples were taken on the second or third day after a work free\nweekend. Blood sampling was repeated 2 days after the first sampling\nNo correlation between exposure and CRP\nRelation observed between SAA and exposure metrics:\nPM1, PM10, and inhalable dust\n[77]\nEmissions from highway maintenance\nHighway maintenance workers at work (Switzerland), Men (n = 18)\nPM2.5, and ultrafine particles during as many as five 24-h-periods. PM2.5 had a mean level of 0.056 mg m−3\nand ultrafine particles 0.112 mg cm−3\nAssociation between PM2.5 and CRP\nAssociation between PM2.5 and SAA\n[82]\n1907476 (8 of 12)\nwww.advancedsciencenews.com\n© 2020 WILEY-VCH Verlag GmbH & Co. KGaA, Weinheim\nwww.small-journal.com\nSmall 2020, 1907476\nVolunteers sitting as passengers in diesel or electric trains; Women (n = 15) and men (n = 14) Sitting as passengers in a diesel train and there being exposed to carbon black at 10.5 µg m−3 and PM2.5 at 0.068 ± 0.032 mg m−3, as compared to sitting as passengers in an electric train and there being\nexposed to only: carbon black at 1.8 µg m−3 and PM2.5 at 0.032 ± 0.007 mg m−3\nNo effect on CRP No effect on SAA [80] And [85]\nCoke-oven emissions\nCoke-oven workers monitored at one time point (Poland), Men (n = 87) Exposed to coke oven emissions and 1-hydroxypyrene measured as a marker of PAH exposure 1-hydroxypyrene (a marker for PAH exposure) was a predictor of CRP\n1-hydroxypyrene (a marker for PAH exposure) was a\npredictor of SAA\n[22]\nEmissions from firefighting\nWildland firefighters at work (United States Forest Service-Savannah River), Sex not reported (n = 10) Smoke (personal monitoring of PM2.5 and CO) during burning season (January to March)\nFirefighters lighting with drip-torches\nhad higher cross-work-shift increases in\nCRP, as compared to firefighters holding a task\ninvolving management of fire boundaries\nFirefighters lighting with drip-torches had higher cross-work-\nshift increases in SAA, as compared to\nfirefighters holding a task involving management of fire\nboundaries\n[83]\nVolunteers participating in a firefighting training course, Women (n = 12) and men (n = 41)\nExposure was a 3-day fire-fighting training course No effect on CRP No effect on SAA [50]\nFirefighters at work, Men (n = 22)\nMeasured before and after a 24-h work shift. No effect on CRP in workers reporting to be involved in fire\nextinction activities (n = 14)\nNo effect on SAA in workers reporting to be involved in fire\nextinction activities (n = 14)\n[81]\nMIG, metal inert gas; PAH, polycyclic aromatic hydrocarbon.\n1907476 (9 of 12)\nwww.advancedsciencenews.com\n© 2020 WILEY-VCH Verlag GmbH & Co. KGaA, Weinheim\nwww.small-journal.com\nImportantly, the cellular signature was hugely different for LPS exposed mice in the single cell data set. Here, mainly leukocytes, in particular dendritic cells/interstitial macrophages, granulocytes and recruited monocytes were responsible for induced Saa3 expression (Figure  3). These preliminary data demonstrate that under aseptic conditions like sterile particleinduced inflammation, the acute phase response can be executed by resident stromal cells. In this context, inflammatory stimulation of rabbit synovial fibroblasts was shown to trigger Saa3 expression[100] and inflammatory stimulation of human epidermal keratinocytes and dermal fibroblasts induced Saa1 and -2.[101] An important role of stromal-derived Saa3 has also been described for cancer-associated fibroblasts, where SAA3 stimulated adenocarcinoma growth in a pancreatic cancer mouse model.[102]\nSaa3 is the most differentially expressed acute phase response gene upon particle exposure in vivo and moreover causally implicated in atherosclerosis, and is therefore the obvious candidate for an acute phase biomarker in in vitro assays. However, its induction could so far not be reproduced in vitro with various models of alveolar epithelial cells or macrophages or their co-culture. LPS however, effectively stimulated the expression of Saa3 in cultured alveolar macrophages and bone marrow derived macrophages (Ana1), matching the in vivo results after LPS stimulation, again demonstrating that different cell types in the lung are required for the responses to specific inflammatory stimuli.[104] Current single cell RNA sequencing experiments from lungs of mice exposed to different nanomaterials shall shed light whether the cell type in which Saa3 is induced depends on the physical chemical characteristics of the nanomaterials.\n9. Conclusion and Perspectives\nInhalation of particles is associated with morbidity and mortality and cardiovascular disease accounts for a large fraction of the particle-induced morbidity and mortality.\nThere is mounting evidence that inhalation of particles induces acute phase response which provides a causal link to risk of cardiovascular disease. The proposed mechanism outlined in Figure 4 has been submitted as an Adverse Outcome Pathway (AOP 237) in the aopwiki.org. The fact that the acute phase response can be\npredicted by the deposited surface area of insoluble materials has important implications, since the particle-induced acute phase response is a means to predict the cardiovascular risk associated with changes of primary particle size. The same information can also be used to guide safe-by-design decisions.\nEpidemiological studies show that even small increases in SAA levels are associated with increased risk of cardiovascular disease and occupational studies show positive correlations between exposure to different types of particles and dusts and CRP and SAA as shown in Table 2. The identification of mesenchymal cells as the candidate cell type for particle-induced Saa3 expression contributes to a first step towards the establishment of an in vitro assay for particle-induced acute phase response.\nIn conclusion, particle-induced acute phase response provides a means for risk assessment of particle-induced cardiovascular disease, and underscores cardiovascular disease as an occupational disease.\nAcknowledgements This work was supported by Danish Centre for Nanosafety 2, and the EU Horizon 2020 project SmartNanoTox, grant agreement no. 686098.\nConflict of Interest The authors declare no conflict of interest.\nKeywords atherosclerosis, cardiovascular diseases, C-reactive protein, nanoparticles, occupational exposure, Serum Amyloid A\nReceived: December 25, 2019 Revised: January 29, 2020\nPublished online:\n[1] D. W.  Dockery, C. A.  Pope III, X.  Xu, J. D.  Spengler, J. H.  Ware, M. E. Fay, B. G. Ferris Jr., F. E. Speizer, N. Engl. J. Med. 1993, 329, 1753. [2] C. A.  Pope III, R. T.  Burnett, M. J.  Thun, E. E.  Calle, D.  Krewski, K. Ito, G. D. Thurston, JAMA, J. Am. Med. Assoc. 2002, 287, 1132.\nSmall 2020, 1907476\n1907476 (10 of 12)\nwww.advancedsciencenews.com\n© 2020 WILEY-VCH Verlag GmbH & Co. KGaA, Weinheim\nwww.small-journal.com\n[3] C. A. Pope III, R. T. Burnett, G. D. Thurston, M. J. Thun, E. E. Calle, D. Krewski, J. J. Godleski, Circulation 2004, 109, 71. [4] C. A.  Pope III, M. L.  Hansen, R. W.  Long, K. R.  Nielsen, N. L.  Eatough, W. E.  Wilson, D. J.  Eatough, Environ. Health Perspect. 2004, 112, 339. [5] C. A.  Pope III, M. J.  Thun, M. M.  Namboodiri, D. W.  Dockery, J. S.  Evans, F. E.  Speizer, C. W.  Heath Jr., Am. J Respir. Crit. Care Med. 1995, 151, 669. [6] L.  Clancy, P.  Goodman, H.  Sinclair, D. W.  Dockery, Lancet 2002, 360, 1210. [7] V.  Stone, M. R.  Miller, M. J.  Clift, A.  Elder, N. L.  Mills, P.  Møller, R. P. Schins, U. Vogel, W. G. Kreyling, K. A. Jensen, T. A. Kuhlbusch, P. E.  Schwarze, P.  Hoet, A.  Pietroiusti, A.  De Vizcaya-Ruiz, A. Baeza-Squiban, C. L. Tran, F. R. Cassee, Environ. Health Perspect. 2016, 125, 106002. [8] O. Schmid, T. Stoeger, J. Aerosol Sci. 2016, 99, 133. [9] G.  Oberdorster, E.  Oberdorster, J.  Oberdorster, Environ. Health\nPerspect. 2005, 113, 823. [10] A.  Elder, R.  Gelein, J. N.  Finkelstein, K. E.  Driscoll, J.  Harkema,\nG. Oberdorster, Toxicol. Sci. 2005, 88, 614. [11] S.  Halappanavar, P.  Jackson, A.  Williams, K. A.  Jensen,\nK. S.  Hougaard, U.  Vogel, C. L.  Yauk, H.  Wallin, Environ. Mol. Mutagen. 2011, 52, 425. [12] R.  Duffin, L.  Tran, D.  Brown, V.  Stone, K.  Donaldson, Inhalation Toxicol. 2007, 19, 849. [13] S. S.  Poulsen, A. T.  Saber, A.  Williams, O.  Andersen, C.  Kobler, R.  Atluri, M. E.  Pozzebon, S. P.  Mucelli, M.  Simion, D.  Rickerby, A.  Mortensen, P.  Jackson, Z. O.  Kyjovska, K.  Molhave, N. R.  Jacobsen, K. A.  Jensen, C. L.  Yauk, H.  Wallin, S. Halappanavar, U. Vogel, Toxicol. Appl. Pharmacol. 2015, 284, 16. [14] S.  Halappanavar, A. T.  Saber, N.  Decan, K. A.  Jensen, D.  Wu, N. R.  Jacobsen, C.  Guo, J.  Rogowski, I. K.  Koponen, M.  Levin, A. M.  Madsen, R.  Atluri, V.  Snitka, R. K.  Birkedal, D.  Rickerby, A. Williams, H. Wallin, C. L. Yauk, U. Vogel, Environ. Mol. Mutagen. 2015, 56, 245. [15] C. Gabay, I. Kushner, N. Engl. J. Med. 1999, 340, 448. [16] G. Taubes, Science 2002, 296, 242. [17] A. T.  Saber, N. R.  Jacobsen, P.  Jackson, S. S.  Poulsen,\nZ. O.  Kyjovska, S.  Halappanavar, C. L.  Yauk, H.  Wallin, U.  Vogel, Wiley Interdiscip. Rev.: Nanomed. Nanobiotechnol. 2014, 6, 517. [18] G. H. Sack Jr., Mol. Med. 2018, 24, 46. [19] M. B. Pepys, G. M. Hirschfield, J. Clin. Invest. 2003, 111, 1805. [20] P. M.  Ridker, C. H.  Hennekens, J. E.  Buring, N.  Rifai, N. Engl.\nJ. Med. 2000, 342, 836. [21] A. M.  Madsen, T.  Thilsing, J.  Baelum, A. H.  Garde, U.  Vogel,\nEnviron. Health 2016, 15, 9. [22] N.  Hadrup, D.  Mielzynska-Svach, A.  Kozlowska, M.  Campisi,\nS. Pavanello, U. Vogel, Environ. Health 2019, 18, 81. [23] J.  Jylhava, A.  Haarala, C.  Eklund, M.  Pertovaara, M.  Kahonen,\nN. Hutri-Kahonen, M. Levula, T. Lehtimaki, R. Huupponen, A. Jula, M. Juonala, J. Viikari, O. Raitakari, M. Hurme, J. Intern. Med. 2009, 266, 286. [24] U. Vogel, Atherosclerosis 2013, 228, 324. [25] J. K.  Pai, K. J.  Mukamal, K. M.  Rexrode, E. B.  Rimm, PLoS One\n2008, 3, e1395. [26] P.  Elliott, J. C.  Chambers, W.  Zhang, R.  Clarke, J. C.  Hopewell,\nJ. F.  Peden, J.  Erdmann, P.  Braund, J. C.  Engert, D.  Bennett, L. Coin, D. Ashby, I. Tzoulaki, I. J. Brown, S. Mt-Isa, M. I. McCarthy, L. Peltonen, N. B. Freimer, M. Farrall, A. Ruokonen, A. Hamsten, N. Lim, P. Froguel, D. M. Waterworth, P. Vollenweider, G. Waeber, M. R.  Jarvelin, V.  Mooser, J.  Scott, A. S.  Hall, H.  Schunkert, S. S.  Anand, R.  Collins, N. J.  Samani, H.  Watkins, J. S.  Kooner, JAMA, J. Am. Med. Assoc. 2009, 302, 37. [27] K. K. Eklund, K. Niemi, P. T. Kovanen, Crit. Rev. Immunol. 2012, 32, 335.\n[28] J. L.  Ather, K.  Ckless, R.  Martin, K. L.  Foley, B. T.  Suratt, J. E.  Boyson, K. A.  Fitzgerald, R. A.  Flavell, S. C.  Eisenbarth, M. E. Poynter, J. Immunol. 2011, 187, 64. [29] V. L.  King, J.  Thompson, L. R.  Tannock, Curr. Opin. Lipidol. 2011, 22, 302. [30] W.  Annema, N.  Nijstad, M.  Tolle, J. F.  de  Boer, R. V.  Buijs, P. Heeringa, M. van der Giet, U. J. Tietge, J. Lipid Res. 2010, 51, 743. [31] F. C. McGillicuddy, M. de la Llera Moya, C. C. Hinkle, M. R. Joshi, E. H.  Chiquoine, J. T.  Billheimer, G. H.  Rothblat, M. P.  Reilly, Circulation 2009, 119, 1135. [32] H. Y. Lee, S. D. Kim, S. H. Baek, J. H. Choi, K. H. Cho, B. A. Zabel, Y. S. Bae, Biochem. Biophys. Res. Commun. 2013, 433, 18. [33] J. C.  Thompson, P. G.  Wilson, P.  Shridas, A.  Ji, B. M.  de, F. C. de Beer, N. R. Webb, L. R. Tannock, Atherosclerosis 2018, 268, 32. [34] Z.  Dong, T.  Wu, W.  Qin, C.  An, Z.  Wang, M.  Zhang, Y.  Zhang, C. Zhang, F. An, Mol. Med. 2011, 17, 1357. [35] J. C. Thompson, C. Jayne, J. Thompson, P. G. Wilson, M. H. Yoder, N. Webb, L. R. Tannock, J. Lipid Res. 2015, 56, 286. [36] M. C.  De Beer, J. M.  Wroblewski, V. P.  Noffsinger, D. L.  Rateri, D. A. Howatt, A. Balakrishnan, A.  Ji, P.  Shridas, J. C. Thompson, D. R.  van der  Westhuyzen, L. R.  Tannock, A.  Daugherty, N. R. Webb, F. C. De Beer, Arterioscler., Thromb., Vasc. Biol. 2014, 34, 255. [37] E. Andre, T. Stoeger, S. Takenaka, M. Bahnweg, B. Ritter, E. Karg, B. Lentner, C. Reinhard, H. Schulz, M. Wjst, Eur. Respir. J. 2006, 28, 275. [38] J. A.  Bourdon, S.  Halappanavar, A. T.  Saber, N. R.  Jacobsen, A. Williams, H. Wallin, U. Vogel, C. L. Yauk, Toxicol. Sci. 2012, 127, 474. [39] S. S.  Poulsen, A. T.  Saber, A.  Mortensen, J.  Szarek, D.  Wu, A.  Williams, O.  Andersen, N. R.  Jacobsen, C. L.  Yauk, H.  Wallin, S. Halappanavar, U. Vogel, Toxicol. Appl. Pharmacol. 2015, 283, 210. [40] K. M.  Bendtsen, A.  Brostrom, A. J.  Koivisto, I.  Koponen, T. Berthing, N. Bertram, K. I. Kling, M. Dal Maso, O. Kangasniemi, M. Poikkimaki, K. Loeschner, P. A. Clausen, H. Wolff, K. A. Jensen, A. T. Saber, U. Vogel, Part. Fibre Toxicol. 2019, 16, 23. [41] S.  Bengtson, K. B.  Knudsen, Z. O.  Kyjovska, T.  Berthing, V. Skaug, M. Levin, I. K. Koponen, A. Shivayogimath, T. J. Booth, B. Alonso, A. Pesquera, A. Zurutuza, B. L. Thomsen, J. T. Troelsen, N. R. Jacobsen, U. Vogel, PLoS One 2017, 12, e0178355. [42] N.  Hadrup, K. B.  Knudsen, T.  Berthing, H.  Wolff, S.  Bengtson, C. Kofoed, R. Espersen, C. Hojgaard, J. R. Winther, M. Willemoes, I.  Wedin, M.  Nuopponen, H.  Alenius, H.  Norppa, H.  Wallin, U. Vogel, Environ. Toxicol. Pharmacol. 2019, 66, 116. [43] A. T.  Saber, S.  Halappanavar, J. K.  Folkmann, J.  Bornholdt, A. M.  Boisen, P.  Moller, A.  Williams, C.  Yauk, U.  Vogel, S.  Loft, H. Wallin, Part. Fibre Toxicol. 2009, 6, 12. [44] A. T.  Saber, J. S.  Lamson, N. R.  Jacobsen, G.  Ravn-Haren, K. S.  Hougaard, A. N.  Nyendi, P.  Wahlberg, A. M.  Madsen, P. Jackson, H. Wallin, U. Vogel, PLoS One 2013, 8, e69020. [45] S. S. Poulsen, K. B. Knudsen, P. Jackson, I. E. Weydahl, A. T. Saber, H. Wallin, U. Vogel, PLoS One 2017, 12, e0174167. [46] M.  Husain, D.  Wu, A. T.  Saber, N.  Decan, N. R.  Jacobsen, A.  Williams, C. L.  Yauk, H.  Wallin, U.  Vogel, S.  Halappanavar, Nanotoxicology 2015, 9, 1013. [47] A. Erdely, T. Hulderman, R. Salmen, A. Liston, P. C. Zeidler-Erdely, D. Schwegler-Berry, V. Castranova, S. Koyama, Y. A. Kim, M. Endo, P. P. Simeonova, Nano Lett. 2009, 9, 36. [48] A. Erdely, A. Liston, R. Salmen-Muniz, T. Hulderman, S. H. Young, P. C.  Zeidler-Erdely, V.  Castranova, P. P.  Simeonova, J. Occup. Environ. Med. 2011, 53, S80. [49] R. Badolato, J. M. Wang, W. J. Murphy, A. R. Lloyd, D. F. Michiel, L. L. Bausserman, D. J. Kelvin, J. J. Oppenheim, J. Exp. Med. 1994, 180, 203.\nSmall 2020, 1907476\n1907476 (11 of 12)\nwww.advancedsciencenews.com\n© 2020 WILEY-VCH Verlag GmbH & Co. KGaA, Weinheim\nwww.small-journal.com\nSmall 2020, 1907476\n[50] M. H. G.  Andersen, A. T.  Saber, P. A.  Clausen, J. E.  Pedersen, M.  Lohr, A.  Kermanizadeh, S.  Loft, N.  Ebbehoj, A. M.  Hansen, P. B. Pedersen, I. K. Koponen, E. C. Norskov, P. Moller, U. Vogel, Mutagenesis 2017, 33, 105. [51] A. T. Saber, K. A. Jensen, N. R. Jacobsen, R. Birkedal, L. Mikkelsen, P. Moller, S. Loft, H. Wallin, U. Vogel, Nanotoxicology 2012, 6, 453. [52] N.  Hadrup, F.  Rahmani, N. R.  Jacobsen, A. T.  Saber, P.  Jackson, S.  Bengtson, A.  Williams, H.  Wallin, S.  Halappanavar, U.  Vogel, Nanotoxicology 2019, 13, 1275. [53] C. E. Chandler, R. K. Ernst, F1000Research 2017, 6, 1334. [54] T.  Xia, M.  Kovochich, M.  Liong, L.  Madler, B.  Gilbert, H.  Shi,\nJ. I. Yeh, J. I. Zink, A. E. Nel, ACS Nano 2008, 2, 2121. [55] H.  Wallin, Z. O.  Kyjovska, S. S.  Poulsen, N. R.  Jacobsen,\nA. T.  Saber, S.  Bengtson, P.  Jackson, U.  Vogel, Mutagenesis 2017, 32, 47. [56] A. T.  Saber, N. R.  Jacobsen, A.  Mortensen, J.  Szarek, P.  Jackson, A. M.  Madsen, K. A.  Jensen, I. K.  Koponen, G.  Brunborg, K. B. Gutzkow, U. Vogel, H. Wallin, Part. Fibre Toxicol. 2012, 9, 4. [57] M.  Husain, A. T.  Saber, C.  Guo, N. R.  Jacobsen, K. A.  Jensen, C. L.  Yauk, A.  Williams, U.  Vogel, H.  Wallin, S.  Halappanavar, Toxicol. Appl. Pharmacol. 2013, 269, 250. [58] A. T.  Saber, A.  Mortensen, J.  Szarek, N. R.  Jacobsen, M.  Levin, I. K. Koponen, K. A. Jensen, U. Vogel, H. Wallin, Hum. Exp. Toxicol. 2019, 38, 11. [59] S. S.  Poulsen, P.  Jackson, K.  Kling, K. B.  Knudsen, V.  Skaug, Z. O. Kyjovska, B. L. Thomsen, P. A. Clausen, R. Atluri, T. Berthing, S.  Bengtson, H.  Wolff, K. A.  Jensen, H.  Wallin, U.  Vogel, Nanotoxicology 2016, 10, 1263. [60] Z. O.  Kyjovska, N. R.  Jacobsen, A. T.  Saber, S.  Bengtson, P. Jackson, H. Wallin, U. Vogel, Mutagenesis 2015, 30, 499. [61] K. K.  Barfod, K. M.  Bendtsen, T.  Berthing, A. J.  Koivisto, S. S.  Poulsen, E.  Segal, E.  Verleysen, J.  Mast, A.  Hollander, K. A. Jensen, K. S. Hougaard, U. Vogel, Environ. Toxicol. Pharmacol. 2020, 73, 103266. [62] A. T.  Saber, A.  Mortensen, J.  Szarek, I. K.  Koponen, M.  Levin, N. R.  Jacobsen, M. E.  Pozzebon, S. P.  Mucelli, D. G.  Rickerby, K.  Kling, R.  Atluri, A. M.  Madsen, P.  Jackson, Z. O.  Kyjovska, U.  Vogel, K. A.  Jensen, H.  Wallin, Part. Fibre Toxicol. 2015, 13, 37. [63] L.  Rahman, D.  Wu, M.  Johnston, A.  William, S.  Halappanavar, Mutagenesis 2016, 32, 59. [64] S.  Halappanavar, L.  Rahman, J.  Nikota, S. S.  Poulsen, Y. B. Ding, P. Jackson, H. Wallin, O. Schmid, U. Vogel, A. Williams, NanoImpact 2019, 14, 100158. [65] F.  Pedregosa, G.  Varoquaux, A.  Gramfort, V.  Michel, B.  Thirion, O.  Grisel, M.  Blondel, P.  Prettenhofer, R.  Weiss, V.  Dubourg, J.  Vanderplas, A.  Passos, D.  Cournapeau, M.  Brucher, M.  Perrot, E. Duchesnay, J. Mach. Learn Res. 2011, 12, 2825. [66] M. I. Greenberg, D. Vearrier, Clin. Toxicol. 2015, 53, 195. [67] E. J. Mueller, D. L. Seger, J. Emerg. Med. 1985, 2, 271. [68] C.  Monse, O.  Hagemeyer, M.  Raulf, B.  Jettkant, K. V.  van,\nB. Kendzia, V. Gering, G. Kappert, T. Weiss, N. Ulrich, E. M. Marek, J. Bunger, T. Bruning, R. Merget, Part. Fibre Toxicol. 2018, 15, 8. [69] U. Vogel, F. R. Cassee, Part. Fibre Toxicol. 2018, 15, 7. [70] R.  Baumann, P.  Brand, A.  Chaker, A.  Markert, I.  Rack,\nS. Davatgarbenam, S. Joraslafsky, B. Gerhards, T. Kraus, M. Gube, Nanotoxicology 2018, 12, 1130. [71] R. Baumann, M. Gube, A. Markert, S. Davatgarbenam, V. Kossack, B. Gerhards, T. Kraus, P. Brand, J. Exposure Sci. Environ. Epidemiol. 2018, 28, 84. [72] R. Baumann, S. Joraslafsky, A. Markert, I. Rack, S. Davatgarbenam, V.  Kossack, B.  Gerhards, T.  Kraus, P.  Brand, M.  Gube, Toxicology 2016, 373, 63. [73] J. Y. Kim, J. C. Chen, P. D. Boyce, D. C. Christiani, Occup. Environ. Med. 2005, 62, 157.\n[74] L. Hartmann, M. Bauer, J. Bertram, M. Gube, K. Lenz, U. Reisgen, T. Schettgen, T. Kraus, P. Brand, Int. J. Hyg. Environ. Health 2014, 217, 160. [75] P.  Brand, M.  Bauer, M.  Gube, K.  Lenz, U.  Reisgen, V. E. Spiegel-Ciobanu, T. Kraus, J. Occup. Environ. Med. 2014, 56, 1. [76] H. Li, M. Hedmer, M. Karedal, J. Bjork, L. Stockfelt, H. Tinnerberg, M. Albin, K. Broberg, PLoS One 2015, 10, e0131648. [77] H.  Westberg, A.  Hedbrant, A.  Persson, I. L.  Bryngelsson, A.  Johansson, A.  Ericsson, B.  Sjogren, L.  Stockfelt, E.  Sarndahl, L. Andersson, Int. Arch. Occup. Environ. Health 2019, 92, 1087. [78] M.  Bonzini, A.  Tripodi, A.  Artoni, L.  Tarantini, B.  Marinelli, P. A.  Bertazzi, P.  Apostoli, A.  Baccarelli, J. Thromb. Haemostasis 2010, 8, 662. [79] H.  Westberg, K.  Elihn, E.  Andersson, B.  Persson, L.  Andersson, I. L. Bryngelsson, C. Karlsson, B. Sjogren, Int. Arch. Occup. Environ. Health 2016, 89, 813. [80] M. H. G.  Andersen, M.  Frederiksen, A. T.  Saber, R. S.  Wils, A. S.  Fonseca, I. K.  Koponen, S.  Johannesson, M.  Roursgaard, S. Loft, P. Moller, U. Vogel, Part. Fibre Toxicol. 2019, 16, 21. [81] M. H. G.  Andersen, A. T.  Saber, J. E.  Pedersen, P. B.  Pedersen, P. A.  Clausen, M.  Lohr, A.  Kermanizadeh, S.  Loft, N. E.  Ebbehoj, A. M.  Hansen, I.  Kalevi Koponen, E. C.  Norskov, U.  Vogel, P. Moller, Environ. Mol. Mutagen. 2018, 59, 539. [82] R. Meier, W. E. Cascio, A. J. Ghio, P. Wild, B. Danuser, M. Riediker, Environ. Health Perspect. 2014, 122, 726. [83] A. M.  Adetona, O.  Adetona, R. M.  Gogal Jr., D.  Diaz-Sanchez, S. L.  Rathbun, L. P.  Naeher, J. Occup. Environ. Med. 2017, 59, 679. [84] A.  Markert, R.  Baumann, B.  Gerhards, M.  Gube, V.  Kossack, T. Kraus, P. Brand, J. Occup. Environ. Med. 2016, 58, 127. [85] M. H. G. Andersen, S. Johannesson, A. S. Fonseca, P. A. Clausen, A. T.  Saber, M.  Roursgaard, K.  Loeschner, I. K.  Koponen, S.  Loft, U. Vogel, P. Moller, Environ. Sci. Technol. 2019, 53, 4579. [86] E. Zakynthinos, N. Pappa, J. Cardiol. 2009, 53, 317. [87] G. D. Lowe, Ann. Periodontol. 2001, 6, 1. [88] Z.  Zhang, L. Y.  Chang, A. K. H.  Lau, T. C.  Chan, C. Y.  Chieh,\nJ. Chan, C. Lin, J. W. Kai, K. Dear, B. C. Y. Zee, E. K. Yeoh, G. Hoek, T. Tam, L. X. Qian, Int. J. Epidemiol. 2017, 46, 1126. [89] M. H. G.  Andersen, A. T.  Saber, P. B.  Pedersen, S.  Loft, A. M.  Hansen, I. K.  Koponen, J. E.  Pedersen, N.  Ebbehoj, E. C.  Norskov, P. A.  Clausen, A. H.  Garde, U.  Vogel, P.  Moller, Environ. Health 2017, 16, 96. [90] A. T.  Saber, S. S.  Poulsen, N.  Hadrup, N. R.  Jacobsen, U.  Vogel, Part. Fibre Toxicol. 2019, 16, 44. [91] S.  Chen, R.  Yin, K.  Mutze, Y.  Yu, S.  Takenaka, M.  Konigshoff, T. Stoeger, Part. Fibre Toxicol. 2015, 13, 33. [92] C.  Sattler, F.  Moritz, S.  Chen, B.  Steer, D.  Kutschke, M.  Irmler, J. Beckers, O. Eickelberg, P. Schmitt-Kopplin, H. Adler, T. Stoeger, Part. Fibre Toxicol. 2017, 14, 2. [93] N. Hadrup, A. T. Saber, Z. O. Kyjovska, N. R. Jacobsen, M. Vippola, E.  Sarlin, Y.  Ding, O.  Schmid, H.  Wallin, K. A.  Jensen, U.  Vogel, Environ. Toxicol. Pharmacol. 2020, 74, 103303. [94] P. H.  Danielsen, K. B.  Knudsen, J.  Strancar, P.  Umek, T.  Koklic, M.  Garvas, E.  Vanhala, S.  Savukoski, Y.  Ding, A. M.  Madsen, N. R.  Jacobsen, I. K.  Weydahl, T.  Berthing, S. S.  Poulsen, O. Schmid, H. Wolff, U. Vogel, Toxicol. Appl. Pharmacol. 2020, 386, 114830. [95] N.  Bech-Thomsen, B.  Munch-Petersen, K.  Lundgren, T.  Poulsen, H. C. Wulf, Acta Derm. Venereol. 1993, 73, 422. [96] P. S. Sos, N. R. Jacobsen, S. Labib, D. Wu, M. Husain, A. Williams, J. P. Bogelund, O. Andersen, C. Kobler, K. Molhave, Z. O. Kyjovska, A. T. Saber, H. Wallin, C. L. Yauk, U. Vogel, S. Halappanavar, PLoS One 2013, 8, e80452. [97] S.  Jeyaseelan, H. W.  Chu, S. K.  Young, G. S.  Worthen, Infect. Immun. 2004, 72, 7247.\n1907476 (12 of 12)\nwww.advancedsciencenews.com\n© 2020 WILEY-VCH Verlag GmbH & Co. KGaA, Weinheim\nwww.small-journal.com\n[98] R. L. Meek, N. Eriksen, E. P. Benditt, Proc. Natl. Acad. Sci. U. S. A. 1992, 89, 7949. [99] C.  Calero, E.  Arellano, J. L.  Lopez-Villalobos, V.  Sanchez-Lopez, N. Moreno-Mata, J. L. Lopez-Campos, BMC Pulm. Med. 2014, 14, 95. [100] T. I. Mitchell, C. I. Coon, C. E. Brinckerhoff, J. Clin. Invest. 1991, 87, 1177. [101] S.  Morizane, A.  Kajita, K.  Mizuno, T.  Takiguchi, K.  Iwatsuki, Clin. Exp. Dermatol. 2019, 44, 40. [102] M.  Djurec, O.  Grana, A.  Lee, K.  Troule, E.  Espinet, L.  Cabras, C.  Navas, M. T.  Blasco, L.  Martin-Diaz, M.  Burdiel, J.  Li, Z.  Liu,\nM.  Vallespinos, F.  Sanchez-Bueno, M. R.  Sprick, A.  Trumpp, B.  Sainz Jr., F.  Al-Shahrour, R.  Rabadan, C.  Guerra, M.  Barbacid, Proc. Natl. Acad. Sci. U. S. A. 2018, 115, E1147. [103] I. Angelidis, L. M. Simon, I. E. Fernandez, M. Strunz, C. H. Mayr, F. R.  Greiffo, G.  Tsitsiridis, M.  Ansari, E.  Graf, T. M.  Strom, M.  Nagendran, T.  Desai, O.  Eickelberg, M.  Mann, F. J.  Theis, H. B. Schiller, Nat. Commun. 2019, 10, 963. [104] S.  Chen, I. E.  Kammerl, O.  Vosyka, T.  Baumann, Y.  Yu, Y.  Wu, M.  Irmler, H. S. Overkleeft, J. Beckers, O. Eickelberg, S. Meiners, T. Stoeger, Cell Death Differ. 2016, 23, 1026.\nSmall 2020, 1907476"
    } ],
    "references" : [ {
      "title" : "Invest",
      "author" : [ "M.B. Pepys", "G.M. Hirschfield", "J. Clin" ],
      "venue" : "2003, 111,",
      "citeRegEx" : "19",
      "shortCiteRegEx" : null,
      "year" : 1805
    }, {
      "title" : "Fibre Toxicol",
      "author" : [ "K.M. Bendtsen", "A. Brostrom", "A.J. Koivisto", "I. Koponen", "T. Berthing", "N. Bertram", "K.I. Kling", "M. Dal Maso", "O. Kangasniemi", "M. Poikkimaki", "K. Loeschner", "P.A. Clausen", "H. Wolff", "K.A. Jensen", "A.T. Saber", "U. Vogel", "Part" ],
      "venue" : null,
      "citeRegEx" : "40",
      "shortCiteRegEx" : "40",
      "year" : 2019
    }, {
      "title" : "Fibre Toxicol",
      "author" : [ "A.T. Saber", "S. Halappanavar", "J.K. Folkmann", "J. Bornholdt", "A.M. Boisen", "P. Moller", "A. Williams", "C. Yauk", "U. Vogel", "S. Loft", "H. Wallin", "Part" ],
      "venue" : null,
      "citeRegEx" : "43",
      "shortCiteRegEx" : "43",
      "year" : 2009
    }, {
      "title" : "Fibre Toxicol",
      "author" : [ "A.T. Saber", "N.R. Jacobsen", "A. Mortensen", "J. Szarek", "P. Jackson", "A.M. Madsen", "K.A. Jensen", "I.K. Koponen", "G. Brunborg", "K.B. Gutzkow", "U. Vogel", "H. Wallin", "Part" ],
      "venue" : null,
      "citeRegEx" : "56",
      "shortCiteRegEx" : "56",
      "year" : 2012
    }, {
      "title" : "Learn Res",
      "author" : [ "F. Pedregosa", "G. Varoquaux", "A. Gramfort", "V. Michel", "B. Thirion", "O. Grisel", "M. Blondel", "P. Prettenhofer", "R. Weiss", "V. Dubourg", "J. Vanderplas", "A. Passos", "D. Cournapeau", "M. Brucher", "M. Perrot", "E. Duchesnay", "J. Mach" ],
      "venue" : "2011, 12,",
      "citeRegEx" : "65",
      "shortCiteRegEx" : null,
      "year" : 2825
    }, {
      "title" : "Fibre Toxicol",
      "author" : [ "C. Monse", "O. Hagemeyer", "M. Raulf", "B. Jettkant", "K.V. van", "B. Kendzia", "V. Gering", "G. Kappert", "T. Weiss", "N. Ulrich", "E.M. Marek", "J. Bunger", "T. Bruning", "R. Merget", "Part" ],
      "venue" : null,
      "citeRegEx" : "68",
      "shortCiteRegEx" : "68",
      "year" : 2018
    }, {
      "title" : "Fibre Toxicol",
      "author" : [ "M.H.G. Andersen", "M. Frederiksen", "A.T. Saber", "R.S. Wils", "A.S. Fonseca", "I.K. Koponen", "S. Johannesson", "M. Roursgaard", "S. Loft", "P. Moller", "U. Vogel", "Part" ],
      "venue" : null,
      "citeRegEx" : "80",
      "shortCiteRegEx" : "80",
      "year" : 2019
    }, {
      "title" : "Invest",
      "author" : [ "T.I. Mitchell", "C.I. Coon", "C.E. Brinckerhoff", "J. Clin" ],
      "venue" : "1991, 87,",
      "citeRegEx" : "100",
      "shortCiteRegEx" : null,
      "year" : 1177
    } ],
    "referenceMentions" : [ {
      "referenceID" : 0,
      "context" : "[18] Interestingly, rats do not express Saa genes, whereas Crp is only moderately inducible in mice.[19] Both SAA and CRP are risk factors for coronary heart disease in prospective, epidemiological studies.",
      "startOffset" : 100,
      "endOffset" : 104
    }, {
      "referenceID" : 2,
      "context" : "[18,29] However, no hepatic acute phase response was detected in mice following inhalation exposure to 20  mg m−3 of Printex 90 carbon black nanoparticles or NIST2975 diesel exhaust particles for 90 min a day, for 4 consecutive days.[43] Instead, inhalation of carbon black and diesel exhaust particles induced a pulmonary acute phase response,[17,44] which for carbon was already detected after 24 h at concentrations of 380 μg m−3.",
      "startOffset" : 233,
      "endOffset" : 237
    }, {
      "referenceID" : 1,
      "context" : "[44] Dose-dependent pulmonary acute phase response has been reported for many different nanoparticles and dusts including TiO2 particles,[14,17,55–58] carbon black,[38] carbon nanotubes,[13,44,45,59] combustion particles,[40,44,60] graphene oxide and reduce graphene oxide,[41] nano-fibrillated celluloses,[42] ZnO nanoparticles,[52] halloysite nanotubes[61] and sanding dust from paint and epoxy composites.",
      "startOffset" : 221,
      "endOffset" : 231
    }, {
      "referenceID" : 5,
      "context" : "[66,67] In a controlled study of 16 healthy volunteers, Christian Monsé et  al.[68] demonstrated that inhalation of nanosized ZnO particles induces dose-dependent acute phase response in humans (Figure 2).",
      "startOffset" : 79,
      "endOffset" : 83
    }, {
      "referenceID" : 5,
      "context" : "[70–76] This is consistent with the strong dose-response relationship observed following inhalation of ZnO nanoparticles.[68] Correlation between dust levels during steel production and iron foundry and blood levels of CRP or SAA have been observed.",
      "startOffset" : 121,
      "endOffset" : 125
    }, {
      "referenceID" : 4,
      "context" : "Acute phase response genes were identified by random forest regression algorithm from scikit-learn python library.[65] Neutrophil percentage values were considered as labels and fold changes of differentially expressed genes as features.",
      "startOffset" : 114,
      "endOffset" : 118
    }, {
      "referenceID" : 5,
      "context" : "[86,87] While bacterial infections increase CRP and SAA levels by more than 1000-fold,[15] inhalation of occupationally relevant doses of ZnO increased CRP and SAA levels by a factor of 10,[68] and the effect of inhaled insoluble particles such as air pollution appears to be even smaller.",
      "startOffset" : 189,
      "endOffset" : 193
    }, {
      "referenceID" : 6,
      "context" : "[88] Such small increments are often difficult to detect even in occupational biomonitoring studies[50,80,89] because large inter-individual variation in basal levels of CRP and SAA hampers the statistical power to detect exposure-related effects.",
      "startOffset" : 99,
      "endOffset" : 109
    }, {
      "referenceID" : 5,
      "context" : "0 International License.[68] Copyright 2018, The Authors, published by Springer.",
      "startOffset" : 24,
      "endOffset" : 28
    }, {
      "referenceID" : 5,
      "context" : "periods and as a final test two to 6 weeks afterwards Increased CRP at 1 and 2 mg m−3 24 h after exposure Increased SAA at 1 and 2 mg m−3 24 h after exposure [68]",
      "startOffset" : 158,
      "endOffset" : 162
    }, {
      "referenceID" : 6,
      "context" : "007 mg m−3 No effect on CRP No effect on SAA [80]",
      "startOffset" : 45,
      "endOffset" : 49
    }, {
      "referenceID" : 7,
      "context" : "In this context, inflammatory stimulation of rabbit synovial fibroblasts was shown to trigger Saa3 expression[100] and inflammatory stimulation of human epidermal keratinocytes and dermal fibroblasts induced Saa1 and -2.",
      "startOffset" : 109,
      "endOffset" : 114
    } ],
    "year" : 2020,
    "abstractText" : "Dr. N. Hadrup, Dr. N. R. Jacobsen, Dr. S. S. Poulsen, Dr. A. T. Saber, Prof. U. Vogel National Research Centre for the Working Environment Copenhagen DK-2100, Denmark E-mail: ubv@nfa.dk Dr. V. Zhernovkov, Prof. B. Kholodenko Systems Biology Ireland University College Dublin Dublin 4, Ireland Dr. C. Voss, Dr. M. Strunz, Dr. M. Ansari, Dr. H. B. Schiller, Dr. T. Stoeger Comprehensive Pneumology Center (CPC)/Institute of Lung Biology and Disease (ILBD) Helmholtz Zentrum München Member of the German Center for Lung Research (DZL) Neuherberg D-85764, Germany Dr. S. Halappanavar Environmental Health Science and Research Bureau Health Canada Ottawa, ON K1A 0K9, Canada Prof. U. Vogel DTU Health Technical University of Denmark Kgs. Lyngby DK-2800, Denmark The ORCID identification number(s) for the author(s) of this article can be found under https://doi.org/10.1002/smll.201907476.",
    "creator" : "Adobe InDesign CS6 (Macintosh)"
  }
}